convertkit/__init__.py
convertkit/client.py
convertkit/exceptions.py
convertkit_py-0.3.0.dist-info/LICENSE
convertkit_py-0.3.0.dist-info/METADATA
convertkit_py-0.3.0.dist-info/WHEEL
convertkit_py-0.3.0.dist-info/top_level.txt
convertkit_py-0.3.0.dist-info/RECORD
