Metadata-Version: 2.1
Name: convertkit-py
Version: 0.3.0
Summary: Python client for the ConvertKit API
Author-email: Andres Kull <andres.a.kull@gmail.com>
Project-URL: Homepage, https://github.com/andreskull/convertkit-py
Project-URL: Bug Tracker, https://github.com/andreskull/convertkit-py/issues
Classifier: Programming Language :: Python :: 3
Classifier: License :: OSI Approved :: MIT License
Classifier: Operating System :: OS Independent
Requires-Python: >=3.11
License-File: LICENSE
Requires-Dist: requests>=2.32.3
Requires-Dist: numpy>=1.26.4
Requires-Dist: python-dotenv>=1.0.1
